[{"SURVEYID":"gb-lry","DEVICEID":"gb-lry-one","TEMP":"24","RH":"70","FLTP":"6","TIMESTAMP":"1682595257","LAT":"29.04068","LNG":"-82.50191"},{"SURVEYID":"gb-lry","DEVICEID":"gb-lry-one","TEMP":"25","RH":"69","FLTP":"6","TIMESTAMP":"1682595357","LAT":"29.04054","LNG":"-82.50219"},{"SURVEYID":"gb-lry","DEVICEID":"gb-lry-one","TEMP":"25","RH":"69","FLTP":"6","TIMESTAMP":"1682595423","LAT":"29.04044","LNG":"-82.50237"},{"SURVEYID":"gb-lry","DEVICEID":"gb-lry-one","TEMP":"25","RH":"68","FLTP":"6","TIMESTAMP":"1682595469","LAT":"29.04065","LNG":"-82.50208"},{"SURVEYID":"gb-lry","DEVICEID":"gb-lry-one","TEMP":"25","RH":"68","FLTP":"6","TIMESTAMP":"1682595515","LAT":"29.04048","LNG":"-82.50232"},{"SURVEYID":"gb-lry","DEVICEID":"gb-lry-one","TEMP":"26","RH":"67","FLTP":"6","TIMESTAMP":"1682595562","LAT":"29.04043","LNG":"-82.50244"},{"SURVEYID":"gb-lry","DEVICEID":"gb-lry-one","TEMP":"26","RH":"67","FLTP":"6","TIMESTAMP":"1682595608","LAT":"29.04052","LNG":"-82.50234"},{"SURVEYID":"gb-lry","DEVICEID":"gb-lry-one","TEMP":"26","RH":"66","FLTP":"6","TIMESTAMP":"1682595658","LAT":"29.04052","LNG":"-82.50227"},{"SURVEYID":"gb-lry","DEVICEID":"gb-lry-one","TEMP":"27","RH":"64","FLTP":"6","TIMESTAMP":"1682595880","LAT":"29.04058","LNG":"-82.50217"},{"SURVEYID":"gb-lry","DEVICEID":"gb-lry-one","TEMP":"27","RH":"63","FLTP":"6","TIMESTAMP":"1682595927","LAT":"29.04072","LNG":"-82.50211"},{"SURVEYID":"gb-lry","DEVICEID":"gb-lry-one","TEMP":"28","RH":"61","FLTP":"6","TIMESTAMP":"1682595981","LAT":"29.04039","LNG":"-82.50225"},{"SURVEYID":"gb-lry","DEVICEID":"gb-lry-one","TEMP":"28","RH":"61","FLTP":"6","TIMESTAMP":"1682596028","LAT":"29.04074","LNG":"-82.50213"},{"SURVEYID":"gb-lry","DEVICEID":"gb-lry-one","TEMP":"28","RH":"60","FLTP":"6","TIMESTAMP":"1682596074","LAT":"29.04055","LNG":"-82.50222"},{"SURVEYID":"gb-lry","DEVICEID":"gb-lry-one","TEMP":"29","RH":"58","FLTP":"6","TIMESTAMP":"1682596188","LAT":"29.04073","LNG":"-82.50208"},{"SURVEYID":"gb-lry","DEVICEID":"gb-lry-one","TEMP":"29","RH":"58","FLTP":"6","TIMESTAMP":"1682596257","LAT":"29.04090","LNG":"-82.50192"},{"SURVEYID":"gb-lry","DEVICEID":"gb-lry-one","TEMP":"29","RH":"57","FLTP":"6","TIMESTAMP":"1682596310","LAT":"29.04070","LNG":"-82.50212"},{"SURVEYID":"gb-lry","DEVICEID":"gb-lry-one","TEMP":"29","RH":"56","FLTP":"6","TIMESTAMP":"1682596409","LAT":"29.04076","LNG":"-82.50227"},{"SURVEYID":"gb-lry","DEVICEID":"gb-lry-one","TEMP":"30","RH":"55","FLTP":"6","TIMESTAMP":"1682596521","LAT":"29.04059","LNG":"-82.50222"},{"SURVEYID":"gb-lry","DEVICEID":"gb-lry-one","TEMP":"30","RH":"55","FLTP":"6","TIMESTAMP":"1682596639","LAT":"29.04074","LNG":"-82.50215"},{"SURVEYID":"gb-lry","DEVICEID":"gb-lry-one","TEMP":"30","RH":"55","FLTP":"6","TIMESTAMP":"1682596699","LAT":"29.04077","LNG":"-82.50222"},{"SURVEYID":"gb-lry","DEVICEID":"gb-lry-one","TEMP":"30","RH":"55","FLTP":"6","TIMESTAMP":"1682596760","LAT":"29.04075","LNG":"-82.50217"},{"SURVEYID":"gb-lry","DEVICEID":"gb-lry-one","TEMP":"30","RH":"54","FLTP":"6","TIMESTAMP":"1682596873","LAT":"29.04066","LNG":"-82.50222"},{"SURVEYID":"gb-lry","DEVICEID":"gb-lry-one","TEMP":"30","RH":"54","FLTP":"6","TIMESTAMP":"1682596945","LAT":"29.04091","LNG":"-82.50212"},{"SURVEYID":"gb-lry","DEVICEID":"gb-lry-one","TEMP":"31","RH":"53","FLTP":"6","TIMESTAMP":"1682596996","LAT":"29.04064","LNG":"-82.50227"},{"SURVEYID":"gb-lry","DEVICEID":"gb-lry-one","TEMP":"31","RH":"53","FLTP":"6","TIMESTAMP":"1682597050","LAT":"29.04059","LNG":"-82.50218"},{"SURVEYID":"gb-lry","DEVICEID":"gb-lry-one","TEMP":"31","RH":"52","FLTP":"6","TIMESTAMP":"1682597222","LAT":"29.04066","LNG":"-82.50221"},{"SURVEYID":"gb-lry","DEVICEID":"gb-lry-one","TEMP":"32","RH":"50","FLTP":"6","TIMESTAMP":"1682597325","LAT":"29.04051","LNG":"-82.50220"},{"SURVEYID":"gb-lry","DEVICEID":"gb-lry-one","TEMP":"32","RH":"49","FLTP":"6","TIMESTAMP":"1682597392","LAT":"29.04044","LNG":"-82.50219"},{"SURVEYID":"gb-lry","DEVICEID":"gb-lry-one","TEMP":"31","RH":"49","FLTP":"6","TIMESTAMP":"1682597552","LAT":"29.04074","LNG":"-82.50208"},{"SURVEYID":"gb-lry","DEVICEID":"gb-lry-one","TEMP":"31","RH":"49","FLTP":"6","TIMESTAMP":"1682597680","LAT":"29.04069","LNG":"-82.50222"},{"SURVEYID":"gb-lry","DEVICEID":"gb-lry-one","TEMP":"30","RH":"49","FLTP":"6","TIMESTAMP":"1682597852","LAT":"29.04048","LNG":"-82.50218"},{"SURVEYID":"gb-lry","DEVICEID":"gb-lry-one","TEMP":"30","RH":"50","FLTP":"6","TIMESTAMP":"1682597959","LAT":"29.04045","LNG":"-82.50213"},{"SURVEYID":"gb-lry","DEVICEID":"gb-lry-one","TEMP":"30","RH":"50","FLTP":"6","TIMESTAMP":"1682598043","LAT":"29.04064","LNG":"-82.50226"},{"SURVEYID":"gb-lry","DEVICEID":"gb-lry-one","TEMP":"29","RH":"50","FLTP":"7","TIMESTAMP":"1682598186","LAT":"29.04094","LNG":"-82.50238"},{"SURVEYID":"gb-lry","DEVICEID":"gb-lry-one","TEMP":"29","RH":"50","FLTP":"7","TIMESTAMP":"1682598323","LAT":"29.04072","LNG":"-82.50227"},{"SURVEYID":"gb-lry","DEVICEID":"gb-lry-one","TEMP":"28","RH":"51","FLTP":"7","TIMESTAMP":"1682598440","LAT":"29.04107","LNG":"-82.50227"},{"SURVEYID":"gb-lry","DEVICEID":"gb-lry-one","TEMP":"28","RH":"51","FLTP":"7","TIMESTAMP":"1682598514","LAT":"29.04094","LNG":"-82.50233"},{"SURVEYID":"gb-lry","DEVICEID":"gb-lry-one","TEMP":"28","RH":"51","FLTP":"7","TIMESTAMP":"1682598567","LAT":"29.04097","LNG":"-82.50237"},{"SURVEYID":"gb-lry","DEVICEID":"gb-lry-one","TEMP":"28","RH":"51","FLTP":"7","TIMESTAMP":"1682598613","LAT":"29.04095","LNG":"-82.50233"},{"SURVEYID":"gb-lry","DEVICEID":"gb-lry-one","TEMP":"28","RH":"51","FLTP":"7","TIMESTAMP":"1682598664","LAT":"29.04094","LNG":"-82.50239"},{"SURVEYID":"gb-lry","DEVICEID":"gb-lry-one","TEMP":"28","RH":"51","FLTP":"7","TIMESTAMP":"1682598714","LAT":"29.04082","LNG":"-82.50229"},{"SURVEYID":"gb-lry","DEVICEID":"gb-lry-one","TEMP":"28","RH":"51","FLTP":"7","TIMESTAMP":"1682598764","LAT":"29.04088","LNG":"-82.50239"},{"SURVEYID":"gb-lry","DEVICEID":"gb-lry-one","TEMP":"28","RH":"51","FLTP":"7","TIMESTAMP":"1682598810","LAT":"29.04090","LNG":"-82.50230"},{"SURVEYID":"gb-lry","DEVICEID":"gb-lry-one","TEMP":"27","RH":"51","FLTP":"7","TIMESTAMP":"1682598857","LAT":"29.04097","LNG":"-82.50235"},{"SURVEYID":"gb-lry","DEVICEID":"gb-lry-one","TEMP":"27","RH":"51","FLTP":"7","TIMESTAMP":"1682598907","LAT":"29.04115","LNG":"-82.50239"},{"SURVEYID":"gb-lry","DEVICEID":"gb-lry-one","TEMP":"27","RH":"51","FLTP":"7","TIMESTAMP":"1682598958","LAT":"29.04082","LNG":"-82.50224"},{"SURVEYID":"gb-lry","DEVICEID":"gb-lry-one","TEMP":"27","RH":"51","FLTP":"7","TIMESTAMP":"1682599057","LAT":"29.04047","LNG":"-82.50140"},{"SURVEYID":"gb-lry","DEVICEID":"gb-lry-one","TEMP":"27","RH":"51","FLTP":"7","TIMESTAMP":"1682599208","LAT":"29.03983","LNG":"-82.50530"},{"SURVEYID":"gb-lry","DEVICEID":"gb-lry-one","TEMP":"27","RH":"51","FLTP":"7","TIMESTAMP":"1682599268","LAT":"29.03905","LNG":"-82.50652"},{"SURVEYID":"gb-lry","DEVICEID":"gb-lry-one","TEMP":"27","RH":"51","FLTP":"7","TIMESTAMP":"1682599326","LAT":"29.03769","LNG":"-82.50916"},{"SURVEYID":"gb-lry","DEVICEID":"gb-lry-one","TEMP":"26","RH":"52","FLTP":"8","TIMESTAMP":"1682599816","LAT":"29.04251","LNG":"-82.53761"},{"SURVEYID":"gb-lry","DEVICEID":"gb-lry-one","TEMP":"26","RH":"53","FLTP":"8","TIMESTAMP":"1682600261","LAT":"29.04278","LNG":"-82.53764"},{"SURVEYID":"gb-lry","DEVICEID":"gb-lry-one","TEMP":"26","RH":"53","FLTP":"8","TIMESTAMP":"1682600323","LAT":"29.04280","LNG":"-82.53759"},{"SURVEYID":"gb-lry","DEVICEID":"gb-lry-one","TEMP":"26","RH":"53","FLTP":"9","TIMESTAMP":"1682600868","LAT":"29.04280","LNG":"-82.53764"},{"SURVEYID":"gb-lry","DEVICEID":"gb-lry-one","TEMP":"27","RH":"53","FLTP":"9","TIMESTAMP":"1682600921","LAT":"29.04281","LNG":"-82.53764"},{"SURVEYID":"gb-lry","DEVICEID":"gb-lry-one","TEMP":"27","RH":"53","FLTP":"9","TIMESTAMP":"1682601020","LAT":"29.04281","LNG":"-82.53757"},{"SURVEYID":"gb-lry","DEVICEID":"gb-lry-one","TEMP":"27","RH":"52","FLTP":"9","TIMESTAMP":"1682601130","LAT":"29.04277","LNG":"-82.53751"},{"SURVEYID":"gb-lry","DEVICEID":"gb-lry-one","TEMP":"27","RH":"52","FLTP":"9","TIMESTAMP":"1682601239","LAT":"29.04280","LNG":"-82.53761"},{"SURVEYID":"gb-lry","DEVICEID":"gb-lry-one","TEMP":"27","RH":"52","FLTP":"9","TIMESTAMP":"1682601312","LAT":"29.04281","LNG":"-82.53762"},{"SURVEYID":"gb-lry","DEVICEID":"gb-lry-one","TEMP":"27","RH":"52","FLTP":"9","TIMESTAMP":"1682601358","LAT":"29.04280","LNG":"-82.53758"},{"SURVEYID":"gb-lry","DEVICEID":"gb-lry-one","TEMP":"28","RH":"54","FLTP":"20","TIMESTAMP":"1682603768","LAT":"29.04284","LNG":"-82.53923"},{"SURVEYID":"gb-lry","DEVICEID":"gb-lry-one","TEMP":"29","RH":"53","FLTP":"20","TIMESTAMP":"1682603867","LAT":"29.04293","LNG":"-82.53932"},{"SURVEYID":"gb-lry","DEVICEID":"gb-lry-one","TEMP":"29","RH":"53","FLTP":"20","TIMESTAMP":"1682604027","LAT":"29.04306","LNG":"-82.53954"},{"SURVEYID":"gb-lry","DEVICEID":"gb-lry-one","TEMP":"29","RH":"53","FLTP":"20","TIMESTAMP":"1682604141","LAT":"29.04314","LNG":"-82.53974"},{"SURVEYID":"gb-lry","DEVICEID":"gb-lry-one","TEMP":"29","RH":"53","FLTP":"20","TIMESTAMP":"1682604219","LAT":"29.04322","LNG":"-82.53986"},{"SURVEYID":"gb-lry","DEVICEID":"gb-lry-one","TEMP":"29","RH":"53","FLTP":"20","TIMESTAMP":"1682604291","LAT":"29.04329","LNG":"-82.53997"},{"SURVEYID":"gb-lry","DEVICEID":"gb-lry-one","TEMP":"29","RH":"53","FLTP":"20","TIMESTAMP":"1682604364","LAT":"29.04334","LNG":"-82.54011"},{"SURVEYID":"gb-lry","DEVICEID":"gb-lry-one","TEMP":"29","RH":"53","FLTP":"20","TIMESTAMP":"1682604437","LAT":"29.04339","LNG":"-82.54025"},{"SURVEYID":"gb-lry","DEVICEID":"gb-lry-one","TEMP":"29","RH":"52","FLTP":"20","TIMESTAMP":"1682604510","LAT":"29.04346","LNG":"-82.54037"},{"SURVEYID":"gb-lry","DEVICEID":"gb-lry-one","TEMP":"29","RH":"52","FLTP":"20","TIMESTAMP":"1682604588","LAT":"29.04352","LNG":"-82.54047"},{"SURVEYID":"gb-lry","DEVICEID":"gb-lry-one","TEMP":"28","RH":"56","FLTP":"20","TIMESTAMP":"1682607492","LAT":"29.04332","LNG":"-82.54675"},{"SURVEYID":"gb-lry","DEVICEID":"gb-lry-one","TEMP":"28","RH":"53","FLTP":"15","TIMESTAMP":"1682602535","LAT":"29.04256","LNG":"-82.53857"},{"SURVEYID":"gb-lry","DEVICEID":"gb-lry-one","TEMP":"28","RH":"53","FLTP":"15","TIMESTAMP":"1682602601","LAT":"29.04253","LNG":"-82.53853"},{"SURVEYID":"gb-lry","DEVICEID":"gb-lry-one","TEMP":"28","RH":"54","FLTP":"16","TIMESTAMP":"1682602737","LAT":"29.04256","LNG":"-82.53856"},{"SURVEYID":"gb-lry","DEVICEID":"gb-lry-one","TEMP":"28","RH":"54","FLTP":"16","TIMESTAMP":"1682602803","LAT":"29.04258","LNG":"-82.53854"},{"SURVEYID":"gb-lry","DEVICEID":"gb-lry-one","TEMP":"28","RH":"54","FLTP":"16","TIMESTAMP":"1682602881","LAT":"29.04256","LNG":"-82.53854"},{"SURVEYID":"gb-lry","DEVICEID":"gb-lry-one","TEMP":"28","RH":"54","FLTP":"17","TIMESTAMP":"1682603020","LAT":"29.04245","LNG":"-82.53844"},{"SURVEYID":"gb-lry","DEVICEID":"gb-lry-one","TEMP":"28","RH":"53","FLTP":"18","TIMESTAMP":"1682603159","LAT":"29.04220","LNG":"-82.53840"},{"SURVEYID":"gb-lry","DEVICEID":"gb-lry-one","TEMP":"28","RH":"53","FLTP":"19","TIMESTAMP":"1682603290","LAT":"29.04237","LNG":"-82.53859"},{"SURVEYID":"gb-lry","DEVICEID":"gb-lry-one","TEMP":"28","RH":"53","FLTP":"19","TIMESTAMP":"1682603373","LAT":"29.04246","LNG":"-82.53877"},{"SURVEYID":"gb-lry","DEVICEID":"gb-lry-one","TEMP":"29","RH":"57","FLTP":"20","TIMESTAMP":"1682607561","LAT":"29.04245","LNG":"-82.54809"},{"SURVEYID":"gb-lry","DEVICEID":"gb-lry-one","TEMP":"28","RH":"53","FLTP":"19","TIMESTAMP":"1682603447","LAT":"29.04252","LNG":"-82.53886"},{"SURVEYID":"gb-lry","DEVICEID":"gb-lry-one","TEMP":"28","RH":"54","FLTP":"20","TIMESTAMP":"1682603581","LAT":"29.04264","LNG":"-82.53896"},{"SURVEYID":"gb-lry","DEVICEID":"gb-lry-one","TEMP":"28","RH":"54","FLTP":"20","TIMESTAMP":"1682603673","LAT":"29.04271","LNG":"-82.53904"},{"SURVEYID":"gb-lry","DEVICEID":"gb-lry-one","TEMP":"29","RH":"53","FLTP":"20","TIMESTAMP":"1682604666","LAT":"29.04364","LNG":"-82.54053"},{"SURVEYID":"gb-lry","DEVICEID":"gb-lry-one","TEMP":"29","RH":"53","FLTP":"20","TIMESTAMP":"1682604739","LAT":"29.04375","LNG":"-82.54063"},{"SURVEYID":"gb-lry","DEVICEID":"gb-lry-one","TEMP":"29","RH":"53","FLTP":"20","TIMESTAMP":"1682604811","LAT":"29.04383","LNG":"-82.54070"},{"SURVEYID":"gb-lry","DEVICEID":"gb-lry-one","TEMP":"28","RH":"53","FLTP":"20","TIMESTAMP":"1682604888","LAT":"29.04391","LNG":"-82.54073"},{"SURVEYID":"gb-lry","DEVICEID":"gb-lry-one","TEMP":"28","RH":"54","FLTP":"20","TIMESTAMP":"1682604960","LAT":"29.04399","LNG":"-82.54082"},{"SURVEYID":"gb-lry","DEVICEID":"gb-lry-one","TEMP":"28","RH":"54","FLTP":"20","TIMESTAMP":"1682605037","LAT":"29.04413","LNG":"-82.54082"},{"SURVEYID":"gb-lry","DEVICEID":"gb-lry-one","TEMP":"29","RH":"56","FLTP":"20","TIMESTAMP":"1682607635","LAT":"29.04246","LNG":"-82.54900"},{"SURVEYID":"gb-lry","DEVICEID":"gb-lry-one","TEMP":"28","RH":"54","FLTP":"20","TIMESTAMP":"1682605109","LAT":"29.04426","LNG":"-82.54086"},{"SURVEYID":"gb-lry","DEVICEID":"gb-lry-one","TEMP":"28","RH":"54","FLTP":"20","TIMESTAMP":"1682605186","LAT":"29.04436","LNG":"-82.54092"},{"SURVEYID":"gb-lry","DEVICEID":"gb-lry-one","TEMP":"28","RH":"54","FLTP":"20","TIMESTAMP":"1682605258","LAT":"29.04442","LNG":"-82.54105"},{"SURVEYID":"gb-lry","DEVICEID":"gb-lry-one","TEMP":"28","RH":"54","FLTP":"20","TIMESTAMP":"1682605331","LAT":"29.04450","LNG":"-82.54111"},{"SURVEYID":"gb-lry","DEVICEID":"gb-lry-one","TEMP":"28","RH":"54","FLTP":"20","TIMESTAMP":"1682605407","LAT":"29.04459","LNG":"-82.54123"},{"SURVEYID":"gb-lry","DEVICEID":"gb-lry-one","TEMP":"28","RH":"54","FLTP":"20","TIMESTAMP":"1682605479","LAT":"29.04463","LNG":"-82.54137"},{"SURVEYID":"gb-lry","DEVICEID":"gb-lry-one","TEMP":"28","RH":"54","FLTP":"20","TIMESTAMP":"1682605552","LAT":"29.04472","LNG":"-82.54147"},{"SURVEYID":"gb-lry","DEVICEID":"gb-lry-one","TEMP":"28","RH":"54","FLTP":"20","TIMESTAMP":"1682605628","LAT":"29.04482","LNG":"-82.54160"},{"SURVEYID":"gb-lry","DEVICEID":"gb-lry-one","TEMP":"28","RH":"54","FLTP":"20","TIMESTAMP":"1682605701","LAT":"29.04487","LNG":"-82.54177"},{"SURVEYID":"gb-lry","DEVICEID":"gb-lry-one","TEMP":"29","RH":"55","FLTP":"20","TIMESTAMP":"1682607705","LAT":"29.04188","LNG":"-82.54871"},{"SURVEYID":"gb-lry","DEVICEID":"gb-lry-one","TEMP":"28","RH":"53","FLTP":"20","TIMESTAMP":"1682605773","LAT":"29.04498","LNG":"-82.54192"},{"SURVEYID":"gb-lry","DEVICEID":"gb-lry-one","TEMP":"27","RH":"53","FLTP":"20","TIMESTAMP":"1682605850","LAT":"29.04508","LNG":"-82.54211"},{"SURVEYID":"gb-lry","DEVICEID":"gb-lry-one","TEMP":"27","RH":"54","FLTP":"20","TIMESTAMP":"1682605922","LAT":"29.04511","LNG":"-82.54221"},{"SURVEYID":"gb-lry","DEVICEID":"gb-lry-one","TEMP":"27","RH":"54","FLTP":"20","TIMESTAMP":"1682605999","LAT":"29.04520","LNG":"-82.54237"},{"SURVEYID":"gb-lry","DEVICEID":"gb-lry-one","TEMP":"27","RH":"54","FLTP":"20","TIMESTAMP":"1682606071","LAT":"29.04529","LNG":"-82.54249"},{"SURVEYID":"gb-lry","DEVICEID":"gb-lry-one","TEMP":"27","RH":"54","FLTP":"20","TIMESTAMP":"1682606148","LAT":"29.04533","LNG":"-82.54256"},{"SURVEYID":"gb-lry","DEVICEID":"gb-lry-one","TEMP":"27","RH":"54","FLTP":"20","TIMESTAMP":"1682606220","LAT":"29.04541","LNG":"-82.54272"},{"SURVEYID":"gb-lry","DEVICEID":"gb-lry-one","TEMP":"27","RH":"55","FLTP":"20","TIMESTAMP":"1682606292","LAT":"29.04550","LNG":"-82.54283"},{"SURVEYID":"gb-lry","DEVICEID":"gb-lry-one","TEMP":"27","RH":"55","FLTP":"20","TIMESTAMP":"1682606369","LAT":"29.04560","LNG":"-82.54296"},{"SURVEYID":"gb-lry","DEVICEID":"gb-lry-one","TEMP":"30","RH":"55","FLTP":"20","TIMESTAMP":"1682607778","LAT":"29.04066","LNG":"-82.54839"},{"SURVEYID":"gb-lry","DEVICEID":"gb-lry-one","TEMP":"30","RH":"55","FLTP":"20","TIMESTAMP":"1682607872","LAT":"29.03658","LNG":"-82.55288"},{"SURVEYID":"gb-lry","DEVICEID":"gb-lry-one","TEMP":"27","RH":"55","FLTP":"20","TIMESTAMP":"1682606441","LAT":"29.04571","LNG":"-82.54305"},{"SURVEYID":"gb-lry","DEVICEID":"gb-lry-one","TEMP":"27","RH":"55","FLTP":"20","TIMESTAMP":"1682606518","LAT":"29.04578","LNG":"-82.54317"},{"SURVEYID":"gb-lry","DEVICEID":"gb-lry-one","TEMP":"27","RH":"55","FLTP":"20","TIMESTAMP":"1682606590","LAT":"29.04591","LNG":"-82.54328"},{"SURVEYID":"gb-lry","DEVICEID":"gb-lry-one","TEMP":"27","RH":"55","FLTP":"20","TIMESTAMP":"1682606667","LAT":"29.04599","LNG":"-82.54339"},{"SURVEYID":"gb-lry","DEVICEID":"gb-lry-one","TEMP":"27","RH":"55","FLTP":"20","TIMESTAMP":"1682606739","LAT":"29.04603","LNG":"-82.54347"},{"SURVEYID":"gb-lry","DEVICEID":"gb-lry-one","TEMP":"27","RH":"55","FLTP":"20","TIMESTAMP":"1682606812","LAT":"29.04618","LNG":"-82.54351"},{"SURVEYID":"gb-lry","DEVICEID":"gb-lry-one","TEMP":"27","RH":"56","FLTP":"20","TIMESTAMP":"1682606888","LAT":"29.04626","LNG":"-82.54361"},{"SURVEYID":"gb-lry","DEVICEID":"gb-lry-one","TEMP":"27","RH":"56","FLTP":"20","TIMESTAMP":"1682606961","LAT":"29.04636","LNG":"-82.54369"},{"SURVEYID":"gb-lry","DEVICEID":"gb-lry-one","TEMP":"30","RH":"54","FLTP":"20","TIMESTAMP":"1682607958","LAT":"29.03618","LNG":"-82.55360"},{"SURVEYID":"gb-lry","DEVICEID":"gb-lry-one","TEMP":"27","RH":"56","FLTP":"20","TIMESTAMP":"1682607037","LAT":"29.04642","LNG":"-82.54379"},{"SURVEYID":"gb-lry","DEVICEID":"gb-lry-one","TEMP":"27","RH":"56","FLTP":"20","TIMESTAMP":"1682607110","LAT":"29.04648","LNG":"-82.54386"},{"SURVEYID":"gb-lry","DEVICEID":"gb-lry-one","TEMP":"28","RH":"57","FLTP":"20","TIMESTAMP":"1682607186","LAT":"29.04643","LNG":"-82.54457"},{"SURVEYID":"gb-lry","DEVICEID":"gb-lry-one","TEMP":"28","RH":"57","FLTP":"20","TIMESTAMP":"1682607259","LAT":"29.04638","LNG":"-82.54538"},{"SURVEYID":"gb-lry","DEVICEID":"gb-lry-one","TEMP":"30","RH":"54","FLTP":"20","TIMESTAMP":"1682608020","LAT":"29.03595","LNG":"-82.55413"},{"SURVEYID":"gb-lry","DEVICEID":"gb-lry-one","TEMP":"30","RH":"55","FLTP":"20","TIMESTAMP":"1682608066","LAT":"29.03593","LNG":"-82.55419"},{"SURVEYID":"gb-lry","DEVICEID":"gb-lry-one","TEMP":"30","RH":"55","FLTP":"20","TIMESTAMP":"1682608117","LAT":"29.03594","LNG":"-82.55421"},{"SURVEYID":"gb-lry","DEVICEID":"gb-lry-one","TEMP":"30","RH":"55","FLTP":"20","TIMESTAMP":"1682608171","LAT":"29.03597","LNG":"-82.55422"},{"SURVEYID":"gb-lry","DEVICEID":"gb-lry-one","TEMP":"30","RH":"55","FLTP":"20","TIMESTAMP":"1682608221","LAT":"29.03600","LNG":"-82.55424"},{"SURVEYID":"gb-lry","DEVICEID":"gb-lry-one","TEMP":"31","RH":"55","FLTP":"20","TIMESTAMP":"1682608269","LAT":"29.03600","LNG":"-82.55424"},{"SURVEYID":"gb-lry","DEVICEID":"gb-lry-one","TEMP":"31","RH":"55","FLTP":"20","TIMESTAMP":"1682608320","LAT":"29.03601","LNG":"-82.55424"},{"SURVEYID":"gb-lry","DEVICEID":"gb-lry-one","TEMP":"31","RH":"55","FLTP":"20","TIMESTAMP":"1682608366","LAT":"29.03603","LNG":"-82.55425"},{"SURVEYID":"gb-lry","DEVICEID":"gb-lry-one","TEMP":"31","RH":"55","FLTP":"20","TIMESTAMP":"1682608421","LAT":"29.03598","LNG":"-82.55421"},{"SURVEYID":"gb-lry","DEVICEID":"gb-lry-one","TEMP":"31","RH":"55","FLTP":"20","TIMESTAMP":"1682608520","LAT":"29.03592","LNG":"-82.55421"},{"SURVEYID":"gb-lry","DEVICEID":"gb-lry-one","TEMP":"31","RH":"55","FLTP":"20","TIMESTAMP":"1682608584","LAT":"29.03597","LNG":"-82.55424"},{"SURVEYID":"gb-lry","DEVICEID":"gb-lry-one","TEMP":"31","RH":"55","FLTP":"20","TIMESTAMP":"1682608633","LAT":"29.03596","LNG":"-82.55421"},{"SURVEYID":"gb-lry","DEVICEID":"gb-lry-one","TEMP":"31","RH":"55","FLTP":"20","TIMESTAMP":"1682608683","LAT":"29.03598","LNG":"-82.55421"},{"SURVEYID":"gb-lry","DEVICEID":"gb-lry-one","TEMP":"32","RH":"56","FLTP":"20","TIMESTAMP":"1682608729","LAT":"29.03601","LNG":"-82.55419"},{"SURVEYID":"gb-lry","DEVICEID":"gb-lry-one","TEMP":"32","RH":"55","FLTP":"20","TIMESTAMP":"1682608832","LAT":"29.03482","LNG":"-82.55500"},{"SURVEYID":"gb-lry","DEVICEID":"gb-lry-one","TEMP":"32","RH":"53","FLTP":"20","TIMESTAMP":"1682609070","LAT":"29.03498","LNG":"-82.56175"},{"SURVEYID":"gb-lry","DEVICEID":"gb-lry-one","TEMP":"32","RH":"54","FLTP":"20","TIMESTAMP":"1682609169","LAT":"29.03509","LNG":"-82.56197"},{"SURVEYID":"gb-lry","DEVICEID":"gb-lry-one","TEMP":"31","RH":"55","FLTP":"20","TIMESTAMP":"1682609290","LAT":"29.03519","LNG":"-82.56221"},{"SURVEYID":"gb-lry","DEVICEID":"gb-lry-one","TEMP":"31","RH":"55","FLTP":"20","TIMESTAMP":"1682609406","LAT":"29.03526","LNG":"-82.56248"},{"SURVEYID":"gb-lry","DEVICEID":"gb-lry-one","TEMP":"31","RH":"55","FLTP":"20","TIMESTAMP":"1682609482","LAT":"29.03534","LNG":"-82.56266"},{"SURVEYID":"gb-lry","DEVICEID":"gb-lry-one","TEMP":"31","RH":"56","FLTP":"20","TIMESTAMP":"1682609559","LAT":"29.03543","LNG":"-82.56287"},{"SURVEYID":"gb-lry","DEVICEID":"gb-lry-one","TEMP":"31","RH":"56","FLTP":"20","TIMESTAMP":"1682609631","LAT":"29.03554","LNG":"-82.56303"},{"SURVEYID":"gb-lry","DEVICEID":"gb-lry-one","TEMP":"31","RH":"57","FLTP":"20","TIMESTAMP":"1682609704","LAT":"29.03557","LNG":"-82.56319"},{"SURVEYID":"gb-lry","DEVICEID":"gb-lry-one","TEMP":"30","RH":"57","FLTP":"20","TIMESTAMP":"1682609776","LAT":"29.03574","LNG":"-82.56331"},{"SURVEYID":"gb-lry","DEVICEID":"gb-lry-one","TEMP":"30","RH":"57","FLTP":"20","TIMESTAMP":"1682609853","LAT":"29.03576","LNG":"-82.56343"},{"SURVEYID":"gb-lry","DEVICEID":"gb-lry-one","TEMP":"30","RH":"68","FLTP":"20","TIMESTAMP":"1682612874","LAT":"29.03482","LNG":"-82.57190"},{"SURVEYID":"gb-lry","DEVICEID":"gb-lry-one","TEMP":"30","RH":"57","FLTP":"20","TIMESTAMP":"1682609930","LAT":"29.03585","LNG":"-82.56349"},{"SURVEYID":"gb-lry","DEVICEID":"gb-lry-one","TEMP":"30","RH":"57","FLTP":"20","TIMESTAMP":"1682610006","LAT":"29.03595","LNG":"-82.56351"},{"SURVEYID":"gb-lry","DEVICEID":"gb-lry-one","TEMP":"30","RH":"57","FLTP":"20","TIMESTAMP":"1682610083","LAT":"29.03600","LNG":"-82.56371"},{"SURVEYID":"gb-lry","DEVICEID":"gb-lry-one","TEMP":"30","RH":"57","FLTP":"20","TIMESTAMP":"1682610155","LAT":"29.03611","LNG":"-82.56390"},{"SURVEYID":"gb-lry","DEVICEID":"gb-lry-one","TEMP":"29","RH":"58","FLTP":"20","TIMESTAMP":"1682610232","LAT":"29.03619","LNG":"-82.56409"},{"SURVEYID":"gb-lry","DEVICEID":"gb-lry-one","TEMP":"29","RH":"58","FLTP":"20","TIMESTAMP":"1682610304","LAT":"29.03627","LNG":"-82.56426"},{"SURVEYID":"gb-lry","DEVICEID":"gb-lry-one","TEMP":"29","RH":"59","FLTP":"20","TIMESTAMP":"1682610377","LAT":"29.03628","LNG":"-82.56436"},{"SURVEYID":"gb-lry","DEVICEID":"gb-lry-one","TEMP":"29","RH":"59","FLTP":"20","TIMESTAMP":"1682610453","LAT":"29.03633","LNG":"-82.56458"},{"SURVEYID":"gb-lry","DEVICEID":"gb-lry-one","TEMP":"29","RH":"59","FLTP":"20","TIMESTAMP":"1682610526","LAT":"29.03643","LNG":"-82.56477"},{"SURVEYID":"gb-lry","DEVICEID":"gb-lry-one","TEMP":"30","RH":"75","FLTP":"20","TIMESTAMP":"1682612939","LAT":"29.03493","LNG":"-82.57193"},{"SURVEYID":"gb-lry","DEVICEID":"gb-lry-one","TEMP":"29","RH":"60","FLTP":"20","TIMESTAMP":"1682610607","LAT":"29.03649","LNG":"-82.56490"},{"SURVEYID":"gb-lry","DEVICEID":"gb-lry-one","TEMP":"29","RH":"60","FLTP":"20","TIMESTAMP":"1682610683","LAT":"29.03659","LNG":"-82.56504"},{"SURVEYID":"gb-lry","DEVICEID":"gb-lry-one","TEMP":"29","RH":"60","FLTP":"20","TIMESTAMP":"1682610760","LAT":"29.03665","LNG":"-82.56522"},{"SURVEYID":"gb-lry","DEVICEID":"gb-lry-one","TEMP":"29","RH":"60","FLTP":"20","TIMESTAMP":"1682610832","LAT":"29.03674","LNG":"-82.56535"},{"SURVEYID":"gb-lry","DEVICEID":"gb-lry-one","TEMP":"29","RH":"59","FLTP":"20","TIMESTAMP":"1682610905","LAT":"29.03681","LNG":"-82.56548"},{"SURVEYID":"gb-lry","DEVICEID":"gb-lry-one","TEMP":"29","RH":"59","FLTP":"20","TIMESTAMP":"1682610981","LAT":"29.03683","LNG":"-82.56567"},{"SURVEYID":"gb-lry","DEVICEID":"gb-lry-one","TEMP":"29","RH":"59","FLTP":"20","TIMESTAMP":"1682611054","LAT":"29.03696","LNG":"-82.56584"},{"SURVEYID":"gb-lry","DEVICEID":"gb-lry-one","TEMP":"28","RH":"60","FLTP":"20","TIMESTAMP":"1682611126","LAT":"29.03699","LNG":"-82.56599"},{"SURVEYID":"gb-lry","DEVICEID":"gb-lry-one","TEMP":"28","RH":"60","FLTP":"20","TIMESTAMP":"1682611203","LAT":"29.03709","LNG":"-82.56609"},{"SURVEYID":"gb-lry","DEVICEID":"gb-lry-one","TEMP":"30","RH":"78","FLTP":"20","TIMESTAMP":"1682613009","LAT":"29.03512","LNG":"-82.57189"},{"SURVEYID":"gb-lry","DEVICEID":"gb-lry-one","TEMP":"28","RH":"60","FLTP":"20","TIMESTAMP":"1682611275","LAT":"29.03717","LNG":"-82.56617"},{"SURVEYID":"gb-lry","DEVICEID":"gb-lry-one","TEMP":"28","RH":"60","FLTP":"20","TIMESTAMP":"1682611347","LAT":"29.03721","LNG":"-82.56623"},{"SURVEYID":"gb-lry","DEVICEID":"gb-lry-one","TEMP":"28","RH":"61","FLTP":"20","TIMESTAMP":"1682611424","LAT":"29.03727","LNG":"-82.56637"},{"SURVEYID":"gb-lry","DEVICEID":"gb-lry-one","TEMP":"28","RH":"60","FLTP":"20","TIMESTAMP":"1682611496","LAT":"29.03735","LNG":"-82.56648"},{"SURVEYID":"gb-lry","DEVICEID":"gb-lry-one","TEMP":"28","RH":"61","FLTP":"20","TIMESTAMP":"1682611573","LAT":"29.03746","LNG":"-82.56662"},{"SURVEYID":"gb-lry","DEVICEID":"gb-lry-one","TEMP":"28","RH":"61","FLTP":"20","TIMESTAMP":"1682611645","LAT":"29.03748","LNG":"-82.56671"},{"SURVEYID":"gb-lry","DEVICEID":"gb-lry-one","TEMP":"29","RH":"62","FLTP":"20","TIMESTAMP":"1682611722","LAT":"29.03752","LNG":"-82.56682"},{"SURVEYID":"gb-lry","DEVICEID":"gb-lry-one","TEMP":"29","RH":"62","FLTP":"20","TIMESTAMP":"1682611799","LAT":"29.03752","LNG":"-82.56687"},{"SURVEYID":"gb-lry","DEVICEID":"gb-lry-one","TEMP":"29","RH":"62","FLTP":"20","TIMESTAMP":"1682611876","LAT":"29.03759","LNG":"-82.56693"},{"SURVEYID":"gb-lry","DEVICEID":"gb-lry-one","TEMP":"31","RH":"79","FLTP":"20","TIMESTAMP":"1682613074","LAT":"29.03521","LNG":"-82.57181"},{"SURVEYID":"gb-lry","DEVICEID":"gb-lry-one","TEMP":"31","RH":"78","FLTP":"20","TIMESTAMP":"1682613150","LAT":"29.03474","LNG":"-82.57143"},{"SURVEYID":"gb-lry","DEVICEID":"gb-lry-one","TEMP":"29","RH":"67","FLTP":"20","TIMESTAMP":"1682611952","LAT":"29.03762","LNG":"-82.56699"},{"SURVEYID":"gb-lry","DEVICEID":"gb-lry-one","TEMP":"29","RH":"72","FLTP":"20","TIMESTAMP":"1682612029","LAT":"29.03762","LNG":"-82.56702"},{"SURVEYID":"gb-lry","DEVICEID":"gb-lry-one","TEMP":"29","RH":"72","FLTP":"20","TIMESTAMP":"1682612106","LAT":"29.03767","LNG":"-82.56699"},{"SURVEYID":"gb-lry","DEVICEID":"gb-lry-one","TEMP":"29","RH":"72","FLTP":"20","TIMESTAMP":"1682612182","LAT":"29.03765","LNG":"-82.56702"},{"SURVEYID":"gb-lry","DEVICEID":"gb-lry-one","TEMP":"30","RH":"72","FLTP":"20","TIMESTAMP":"1682612259","LAT":"29.03765","LNG":"-82.56705"},{"SURVEYID":"gb-lry","DEVICEID":"gb-lry-one","TEMP":"30","RH":"72","FLTP":"20","TIMESTAMP":"1682612336","LAT":"29.03766","LNG":"-82.56701"},{"SURVEYID":"gb-lry","DEVICEID":"gb-lry-one","TEMP":"30","RH":"70","FLTP":"20","TIMESTAMP":"1682612408","LAT":"29.03752","LNG":"-82.56709"},{"SURVEYID":"gb-lry","DEVICEID":"gb-lry-one","TEMP":"30","RH":"69","FLTP":"20","TIMESTAMP":"1682612489","LAT":"29.03746","LNG":"-82.56715"},{"SURVEYID":"gb-lry","DEVICEID":"gb-lry-one","TEMP":"31","RH":"78","FLTP":"20","TIMESTAMP":"1682613246","LAT":"29.03336","LNG":"-82.57095"},{"SURVEYID":"gb-lry","DEVICEID":"gb-lry-one","TEMP":"30","RH":"67","FLTP":"20","TIMESTAMP":"1682612570","LAT":"29.03728","LNG":"-82.56741"},{"SURVEYID":"gb-lry","DEVICEID":"gb-lry-one","TEMP":"30","RH":"69","FLTP":"20","TIMESTAMP":"1682612651","LAT":"29.03640","LNG":"-82.56851"},{"SURVEYID":"gb-lry","DEVICEID":"gb-lry-one","TEMP":"30","RH":"72","FLTP":"20","TIMESTAMP":"1682612777","LAT":"29.03528","LNG":"-82.57106"},{"SURVEYID":"gb-lry","DEVICEID":"gb-lry-one","TEMP":"31","RH":"79","FLTP":"20","TIMESTAMP":"1682613300","LAT":"29.03436","LNG":"-82.56751"},{"SURVEYID":"gb-lry","DEVICEID":"gb-lry-one","TEMP":"31","RH":"80","FLTP":"20","TIMESTAMP":"1682613403","LAT":"29.03521","LNG":"-82.56000"},{"SURVEYID":"gb-lry","DEVICEID":"gb-lry-one","TEMP":"31","RH":"80","FLTP":"20","TIMESTAMP":"1682613469","LAT":"29.03399","LNG":"-82.55608"},{"SURVEYID":"gb-lry","DEVICEID":"gb-lry-one","TEMP":"31","RH":"80","FLTP":"20","TIMESTAMP":"1682613519","LAT":"29.03677","LNG":"-82.55270"},{"SURVEYID":"gb-lry","DEVICEID":"gb-lry-one","TEMP":"31","RH":"79","FLTP":"20","TIMESTAMP":"1682613567","LAT":"29.03979","LNG":"-82.54917"},{"SURVEYID":"gb-lry","DEVICEID":"gb-lry-one","TEMP":"31","RH":"79","FLTP":"20","TIMESTAMP":"1682613618","LAT":"29.04226","LNG":"-82.54420"},{"SURVEYID":"gb-lry","DEVICEID":"gb-lry-one","TEMP":"31","RH":"79","FLTP":"20","TIMESTAMP":"1682613712","LAT":"29.04173","LNG":"-82.53608"},{"SURVEYID":"gb-lry","DEVICEID":"gb-lry-one","TEMP":"31","RH":"79","FLTP":"20","TIMESTAMP":"1682613824","LAT":"29.04300","LNG":"-82.52668"},{"SURVEYID":"gb-lry","DEVICEID":"gb-lry-one","TEMP":"31","RH":"79","FLTP":"20","TIMESTAMP":"1682613898","LAT":"29.03971","LNG":"-82.52217"},{"SURVEYID":"gb-lry","DEVICEID":"gb-lry-one","TEMP":"31","RH":"80","FLTP":"20","TIMESTAMP":"1682614001","LAT":"29.04374","LNG":"-82.51424"},{"SURVEYID":"gb-lry","DEVICEID":"gb-lry-one","TEMP":"31","RH":"80","FLTP":"20","TIMESTAMP":"1682614078","LAT":"29.04118","LNG":"-82.50935"},{"SURVEYID":"gb-lry","DEVICEID":"gb-lry-one","TEMP":"31","RH":"80","FLTP":"20","TIMESTAMP":"1682614150","LAT":"29.03906","LNG":"-82.50629"},{"SURVEYID":"gb-lry","DEVICEID":"gb-lry-one","TEMP":"32","RH":"80","FLTP":"20","TIMESTAMP":"1682614222","LAT":"29.04116","LNG":"-82.50273"},{"SURVEYID":"gb-lry","DEVICEID":"gb-lry-one","TEMP":"32","RH":"79","FLTP":"20","TIMESTAMP":"1682614295","LAT":"29.04106","LNG":"-82.50222"},{"SURVEYID":"gb-lry","DEVICEID":"gb-lry-one","TEMP":"32","RH":"80","FLTP":"20","TIMESTAMP":"1682614371","LAT":"29.04105","LNG":"-82.50226"},{"SURVEYID":"gb-lry","DEVICEID":"gb-lry-one","TEMP":"32","RH":"80","FLTP":"20","TIMESTAMP":"1682614444","LAT":"29.04104","LNG":"-82.50221"},{"SURVEYID":"gb-lry","DEVICEID":"gb-lry-one","TEMP":"32","RH":"80","FLTP":"20","TIMESTAMP":"1682614520","LAT":"29.04100","LNG":"-82.50225"},{"SURVEYID":"gb-lry","DEVICEID":"gb-lry-one","TEMP":"32","RH":"80","FLTP":"20","TIMESTAMP":"1682614597","LAT":"29.04108","LNG":"-82.50227"},{"SURVEYID":"gb-lry","DEVICEID":"gb-lry-one","TEMP":"32","RH":"80","FLTP":"20","TIMESTAMP":"1682614674","LAT":"29.04098","LNG":"-82.50227"},{"SURVEYID":"gb-lry","DEVICEID":"gb-lry-one","TEMP":"32","RH":"81","FLTP":"20","TIMESTAMP":"1682614746","LAT":"29.04096","LNG":"-82.50220"},{"SURVEYID":"gb-lry","DEVICEID":"gb-lry-one","TEMP":"32","RH":"81","FLTP":"20","TIMESTAMP":"1682614823","LAT":"29.04103","LNG":"-82.50234"},{"SURVEYID":"gb-lry","DEVICEID":"gb-lry-one","TEMP":"32","RH":"81","FLTP":"20","TIMESTAMP":"1682614895","LAT":"29.04046","LNG":"-82.50234"},{"SURVEYID":"gb-lry","DEVICEID":"gb-lry-one","TEMP":"32","RH":"82","FLTP":"20","TIMESTAMP":"1682614972","LAT":"29.04053","LNG":"-82.50220"},{"SURVEYID":"gb-lry","DEVICEID":"gb-lry-one","TEMP":"32","RH":"82","FLTP":"20","TIMESTAMP":"1682615057","LAT":"29.04049","LNG":"-82.50227"},{"SURVEYID":"gb-lry","DEVICEID":"gb-lry-one","TEMP":"32","RH":"83","FLTP":"20","TIMESTAMP":"1682615138","LAT":"29.04044","LNG":"-82.50216"},{"SURVEYID":"gb-lry","DEVICEID":"gb-lry-one","TEMP":"32","RH":"83","FLTP":"20","TIMESTAMP":"1682615224","LAT":"29.04057","LNG":"-82.50256"},{"SURVEYID":"gb-lry","DEVICEID":"gb-lry-one","TEMP":"32","RH":"83","FLTP":"20","TIMESTAMP":"1682615313","LAT":"29.04056","LNG":"-82.50255"},{"SURVEYID":"gb-lry","DEVICEID":"gb-lry-one","TEMP":"32","RH":"83","FLTP":"20","TIMESTAMP":"1682615394","LAT":"29.04061","LNG":"-82.50213"},{"SURVEYID":"gb-lry","DEVICEID":"gb-lry-one","TEMP":"32","RH":"83","FLTP":"20","TIMESTAMP":"1682615475","LAT":"29.04057","LNG":"-82.50230"},{"SURVEYID":"gb-lry","DEVICEID":"gb-lry-one","TEMP":"32","RH":"83","FLTP":"20","TIMESTAMP":"1682615557","LAT":"29.04052","LNG":"-82.50218"},{"SURVEYID":"gb-lry","DEVICEID":"gb-lry-one","TEMP":"32","RH":"83","FLTP":"20","TIMESTAMP":"1682615642","LAT":"29.04053","LNG":"-82.50225"},{"SURVEYID":"gb-lry","DEVICEID":"gb-lry-one","TEMP":"32","RH":"83","FLTP":"20","TIMESTAMP":"1682615740","LAT":"29.04061","LNG":"-82.50224"},{"SURVEYID":"gb-lry","DEVICEID":"gb-lry-one","TEMP":"32","RH":"83","FLTP":"20","TIMESTAMP":"1682615822","LAT":"29.04059","LNG":"-82.50230"},{"SURVEYID":"gb-lry","DEVICEID":"gb-lry-one","TEMP":"32","RH":"83","FLTP":"20","TIMESTAMP":"1682615903","LAT":"29.04054","LNG":"-82.50247"},{"SURVEYID":"gb-lry","DEVICEID":"gb-lry-one","TEMP":"32","RH":"83","FLTP":"20","TIMESTAMP":"1682615979","LAT":"29.04057","LNG":"-82.50238"},{"SURVEYID":"gb-lry","DEVICEID":"gb-lry-one","TEMP":"32","RH":"84","FLTP":"20","TIMESTAMP":"1682616060","LAT":"29.04062","LNG":"-82.50226"},{"SURVEYID":"gb-lry","DEVICEID":"gb-lry-one","TEMP":"32","RH":"84","FLTP":"20","TIMESTAMP":"1682616146","LAT":"29.03819","LNG":"-82.50224"},{"SURVEYID":"gb-lry","DEVICEID":"gb-lry-one","TEMP":"32","RH":"83","FLTP":"20","TIMESTAMP":"1682616222","LAT":"29.03606","LNG":"-82.50082"},{"SURVEYID":"gb-lry","DEVICEID":"gb-lry-one","TEMP":"32","RH":"84","FLTP":"20","TIMESTAMP":"1682616304","LAT":"29.03919","LNG":"-82.48698"},{"SURVEYID":"gb-lry","DEVICEID":"gb-lry-one","TEMP":"32","RH":"84","FLTP":"20","TIMESTAMP":"1682616385","LAT":"29.04313","LNG":"-82.47379"},{"SURVEYID":"gb-lry","DEVICEID":"gb-lry-one","TEMP":"32","RH":"84","FLTP":"20","TIMESTAMP":"1682616479","LAT":"29.04912","LNG":"-82.46163"},{"SURVEYID":"gb-lry","DEVICEID":"gb-lry-one","TEMP":"32","RH":"84","FLTP":"20","TIMESTAMP":"1682616560","LAT":"29.04965","LNG":"-82.46101"},{"SURVEYID":"gb-lry","DEVICEID":"gb-lry-one","TEMP":"32","RH":"84","FLTP":"20","TIMESTAMP":"1682616641","LAT":"29.05813","LNG":"-82.45537"},{"SURVEYID":"gb-lry","DEVICEID":"gb-lry-one","TEMP":"32","RH":"84","FLTP":"20","TIMESTAMP":"1682616718","LAT":"29.07033","LNG":"-82.45336"},{"SURVEYID":"gb-lry","DEVICEID":"gb-lry-one","TEMP":"32","RH":"84","FLTP":"20","TIMESTAMP":"1682616794","LAT":"29.08039","LNG":"-82.45243"},{"SURVEYID":"gb-lry","DEVICEID":"gb-lry-one","TEMP":"32","RH":"85","FLTP":"20","TIMESTAMP":"1682616875","LAT":"29.09708","LNG":"-82.45109"},{"SURVEYID":"gb-lry","DEVICEID":"gb-lry-one","TEMP":"31","RH":"85","FLTP":"20","TIMESTAMP":"1682616956","LAT":"29.11273","LNG":"-82.44833"},{"SURVEYID":"gb-lry","DEVICEID":"gb-lry-one","TEMP":"31","RH":"85","FLTP":"20","TIMESTAMP":"1682617037","LAT":"29.12164","LNG":"-82.44650"},{"SURVEYID":"gb-lry","DEVICEID":"gb-lry-one","TEMP":"32","RH":"85","FLTP":"20","TIMESTAMP":"1682617127","LAT":"29.12180","LNG":"-82.44630"},{"SURVEYID":"gb-lry","DEVICEID":"gb-lry-one","TEMP":"32","RH":"86","FLTP":"20","TIMESTAMP":"1682617213","LAT":"29.13090","LNG":"-82.44472"},{"SURVEYID":"gb-lry","DEVICEID":"gb-lry-one","TEMP":"32","RH":"86","FLTP":"20","TIMESTAMP":"1682617289","LAT":"29.14461","LNG":"-82.44209"},{"SURVEYID":"gb-lry","DEVICEID":"gb-lry-one","TEMP":"32","RH":"86","FLTP":"20","TIMESTAMP":"1682617379","LAT":"29.16293","LNG":"-82.44037"},{"SURVEYID":"gb-lry","DEVICEID":"gb-lry-one","TEMP":"32","RH":"86","FLTP":"20","TIMESTAMP":"1682617469","LAT":"29.18293","LNG":"-82.43919"},{"SURVEYID":"gb-lry","DEVICEID":"gb-lry-one","TEMP":"32","RH":"86","FLTP":"20","TIMESTAMP":"1682617554","LAT":"29.20150","LNG":"-82.43755"},{"SURVEYID":"gb-lry","DEVICEID":"gb-lry-one","TEMP":"32","RH":"86","FLTP":"20","TIMESTAMP":"1682617635","LAT":"29.21918","LNG":"-82.44071"},{"SURVEYID":"gb-lry","DEVICEID":"gb-lry-one","TEMP":"32","RH":"87","FLTP":"20","TIMESTAMP":"1682617716","LAT":"29.23891","LNG":"-82.44121"},{"SURVEYID":"gb-lry","DEVICEID":"gb-lry-one","TEMP":"32","RH":"87","FLTP":"20","TIMESTAMP":"1682617793","LAT":"29.25759","LNG":"-82.44158"},{"SURVEYID":"gb-lry","DEVICEID":"gb-lry-one","TEMP":"32","RH":"87","FLTP":"20","TIMESTAMP":"1682617900","LAT":"29.28356","LNG":"-82.44519"},{"SURVEYID":"gb-lry","DEVICEID":"gb-lry-one","TEMP":"32","RH":"87","FLTP":"20","TIMESTAMP":"1682617981","LAT":"29.30338","LNG":"-82.44920"},{"SURVEYID":"gb-lry","DEVICEID":"gb-lry-one","TEMP":"32","RH":"87","FLTP":"20","TIMESTAMP":"1682618063","LAT":"29.32355","LNG":"-82.45329"},{"SURVEYID":"gb-lry","DEVICEID":"gb-lry-one","TEMP":"32","RH":"87","FLTP":"20","TIMESTAMP":"1682618139","LAT":"29.34225","LNG":"-82.45575"},{"SURVEYID":"gb-lry","DEVICEID":"gb-lry-one","TEMP":"32","RH":"87","FLTP":"20","TIMESTAMP":"1682618220","LAT":"29.36149","LNG":"-82.45575"},{"SURVEYID":"gb-lry","DEVICEID":"gb-lry-one","TEMP":"32","RH":"87","FLTP":"20","TIMESTAMP":"1682618301","LAT":"29.37571","LNG":"-82.45577"},{"SURVEYID":"gb-lry","DEVICEID":"gb-lry-one","TEMP":"32","RH":"87","FLTP":"20","TIMESTAMP":"1682618378","LAT":"29.38610","LNG":"-82.45500"},{"SURVEYID":"gb-lry","DEVICEID":"gb-lry-one","TEMP":"33","RH":"87","FLTP":"20","TIMESTAMP":"1682618459","LAT":"29.38798","LNG":"-82.44746"},{"SURVEYID":"gb-lry","DEVICEID":"gb-lry-one","TEMP":"33","RH":"88","FLTP":"20","TIMESTAMP":"1682618540","LAT":"29.39954","LNG":"-82.44116"},{"SURVEYID":"gb-lry","DEVICEID":"gb-lry-one","TEMP":"33","RH":"88","FLTP":"20","TIMESTAMP":"1682618621","LAT":"29.41488","LNG":"-82.43008"},{"SURVEYID":"gb-lry","DEVICEID":"gb-lry-one","TEMP":"33","RH":"88","FLTP":"20","TIMESTAMP":"1682618702","LAT":"29.43237","LNG":"-82.41655"},{"SURVEYID":"gb-lry","DEVICEID":"gb-lry-one","TEMP":"33","RH":"88","FLTP":"20","TIMESTAMP":"1682618788","LAT":"29.45305","LNG":"-82.41062"},{"SURVEYID":"gb-lry","DEVICEID":"gb-lry-one","TEMP":"33","RH":"88","FLTP":"20","TIMESTAMP":"1682618869","LAT":"29.47379","LNG":"-82.41457"},{"SURVEYID":"gb-lry","DEVICEID":"gb-lry-one","TEMP":"33","RH":"88","FLTP":"20","TIMESTAMP":"1682618954","LAT":"29.49451","LNG":"-82.40684"},{"SURVEYID":"gb-lry","DEVICEID":"gb-lry-one","TEMP":"33","RH":"88","FLTP":"20","TIMESTAMP":"1682619040","LAT":"29.51662","LNG":"-82.40633"},{"SURVEYID":"gb-lry","DEVICEID":"gb-lry-one","TEMP":"33","RH":"88","FLTP":"20","TIMESTAMP":"1682619125","LAT":"29.53853","LNG":"-82.40127"},{"SURVEYID":"gb-lry","DEVICEID":"gb-lry-one","TEMP":"33","RH":"88","FLTP":"20","TIMESTAMP":"1682619215","LAT":"29.55927","LNG":"-82.39146"},{"SURVEYID":"gb-lry","DEVICEID":"gb-lry-one","TEMP":"34","RH":"88","FLTP":"20","TIMESTAMP":"1682619344","LAT":"29.59121","LNG":"-82.38715"},{"SURVEYID":"gb-lry","DEVICEID":"gb-lry-one","TEMP":"34","RH":"88","FLTP":"20","TIMESTAMP":"1682619451","LAT":"29.60115","LNG":"-82.37453"},{"SURVEYID":"gb-lry","DEVICEID":"gb-lry-one","TEMP":"34","RH":"88","FLTP":"20","TIMESTAMP":"1682619541","LAT":"29.60507","LNG":"-82.37114"},{"SURVEYID":"gb-lry","DEVICEID":"gb-lry-one","TEMP":"34","RH":"88","FLTP":"20","TIMESTAMP":"1682619622","LAT":"29.61989","LNG":"-82.37274"},{"SURVEYID":"gb-lry","DEVICEID":"gb-lry-one","TEMP":"34","RH":"88","FLTP":"20","TIMESTAMP":"1682619703","LAT":"29.62316","LNG":"-82.37250"},{"SURVEYID":"gb-lry","DEVICEID":"gb-lry-one","TEMP":"34","RH":"88","FLTP":"20","TIMESTAMP":"1682619780","LAT":"29.63401","LNG":"-82.37243"},{"SURVEYID":"gb-lry","DEVICEID":"gb-lry-one","TEMP":"34","RH":"88","FLTP":"20","TIMESTAMP":"1682619857","LAT":"29.63751","LNG":"-82.36861"},{"SURVEYID":"gb-lry","DEVICEID":"gb-lry-one","TEMP":"34","RH":"88","FLTP":"20","TIMESTAMP":"1682619938","LAT":"29.63752","LNG":"-82.36853"},{"SURVEYID":"gb-lry","DEVICEID":"gb-lry-one","TEMP":"34","RH":"88","FLTP":"20","TIMESTAMP":"1682620019","LAT":"29.63750","LNG":"-82.36852"},{"SURVEYID":"gb-lry","DEVICEID":"gb-lry-one","TEMP":"34","RH":"88","FLTP":"20","TIMESTAMP":"1682620100","LAT":"29.63746","LNG":"-82.36861"},{"SURVEYID":"gb-lry","DEVICEID":"gb-lry-one","TEMP":"34","RH":"88","FLTP":"20","TIMESTAMP":"1682620181","LAT":"29.63745","LNG":"-82.36871"},{"SURVEYID":"gb-lry","DEVICEID":"gb-lry-one","TEMP":"35","RH":"88","FLTP":"20","TIMESTAMP":"1682620262","LAT":"29.63748","LNG":"-82.36871"},{"SURVEYID":"gb-lry","DEVICEID":"gb-lry-one","TEMP":"35","RH":"88","FLTP":"20","TIMESTAMP":"1682620348","LAT":"29.63745","LNG":"-82.36869"},{"SURVEYID":"gb-lry","DEVICEID":"gb-lry-one","TEMP":"35","RH":"88","FLTP":"20","TIMESTAMP":"1682620433","LAT":"29.63739","LNG":"-82.36880"},{"SURVEYID":"gb-lry","DEVICEID":"gb-lry-one","TEMP":"35","RH":"88","FLTP":"20","TIMESTAMP":"1682620518","LAT":"29.63736","LNG":"-82.36881"},{"SURVEYID":"gb-lry","DEVICEID":"gb-lry-one","TEMP":"35","RH":"88","FLTP":"20","TIMESTAMP":"1682620608","LAT":"29.63738","LNG":"-82.36870"},{"SURVEYID":"gb-lry","DEVICEID":"gb-lry-one","TEMP":"35","RH":"89","FLTP":"20","TIMESTAMP":"1682620711","LAT":"29.63753","LNG":"-82.36859"},{"SURVEYID":"gb-lry","DEVICEID":"gb-lry-one","TEMP":"35","RH":"89","FLTP":"20","TIMESTAMP":"1682620792","LAT":"29.63753","LNG":"-82.36880"},{"SURVEYID":"gb-lry","DEVICEID":"gb-lry-one","TEMP":"35","RH":"89","FLTP":"20","TIMESTAMP":"1682620869","LAT":"29.63766","LNG":"-82.36429"},{"SURVEYID":"gb-lry","DEVICEID":"gb-lry-one","TEMP":"35","RH":"89","FLTP":"20","TIMESTAMP":"1682620946","LAT":"29.63764","LNG":"-82.35907"},{"SURVEYID":"gb-lry","DEVICEID":"gb-lry-one","TEMP":"35","RH":"89","FLTP":"20","TIMESTAMP":"1682621023","LAT":"29.63895","LNG":"-82.35080"},{"SURVEYID":"gb-lry","DEVICEID":"gb-lry-one","TEMP":"35","RH":"88","FLTP":"20","TIMESTAMP":"1682621112","LAT":"29.64046","LNG":"-82.34627"},{"SURVEYID":"gb-lry","DEVICEID":"gb-lry-one","TEMP":"35","RH":"88","FLTP":"20","TIMESTAMP":"1682621189","LAT":"29.64433","LNG":"-82.34599"},{"SURVEYID":"gb-lry","DEVICEID":"gb-lry-one","TEMP":"35","RH":"88","FLTP":"20","TIMESTAMP":"1682621266","LAT":"29.64433","LNG":"-82.34592"},{"SURVEYID":"gb-lry","DEVICEID":"gb-lry-one","TEMP":"35","RH":"88","FLTP":"20","TIMESTAMP":"1682621343","LAT":"29.64420","LNG":"-82.34584"},{"SURVEYID":"gb-lry","DEVICEID":"gb-lry-one","TEMP":"35","RH":"88","FLTP":"20","TIMESTAMP":"1682621419","LAT":"29.64429","LNG":"-82.34592"},{"SURVEYID":"gb-lry","DEVICEID":"gb-lry-one","TEMP":"35","RH":"88","FLTP":"20","TIMESTAMP":"1682621500","LAT":"29.64434","LNG":"-82.34599"},{"SURVEYID":"gb-lry","DEVICEID":"gb-lry-one","TEMP":"35","RH":"88","FLTP":"20","TIMESTAMP":"1682621590","LAT":"29.64439","LNG":"-82.34602"},{"SURVEYID":"gb-lry","DEVICEID":"gb-lry-one","TEMP":"35","RH":"88","FLTP":"20","TIMESTAMP":"1682621676","LAT":"29.64434","LNG":"-82.34588"},{"SURVEYID":"gb-lry","DEVICEID":"gb-lry-one","TEMP":"35","RH":"88","FLTP":"20","TIMESTAMP":"1682621757","LAT":"29.64435","LNG":"-82.34589"},{"SURVEYID":"gb-lry","DEVICEID":"gb-lry-one","TEMP":"35","RH":"88","FLTP":"20","TIMESTAMP":"1682621834","LAT":"29.64433","LNG":"-82.34591"},{"SURVEYID":"gb-lry","DEVICEID":"gb-lry-one","TEMP":"35","RH":"88","FLTP":"20","TIMESTAMP":"1682621910","LAT":"29.64420","LNG":"-82.34597"},{"SURVEYID":"gb-lry","DEVICEID":"gb-lry-one","TEMP":"35","RH":"88","FLTP":"20","TIMESTAMP":"1682621992","LAT":"29.64423","LNG":"-82.34591"},{"SURVEYID":"gb-lry","DEVICEID":"gb-lry-one","TEMP":"35","RH":"88","FLTP":"20","TIMESTAMP":"1682622068","LAT":"29.64429","LNG":"-82.34609"},{"SURVEYID":"gb-lry","DEVICEID":"gb-lry-one","TEMP":"35","RH":"88","FLTP":"20","TIMESTAMP":"1682622149","LAT":"29.64433","LNG":"-82.34592"},{"SURVEYID":"gb-lry","DEVICEID":"gb-lry-one","TEMP":"35","RH":"88","FLTP":"21","TIMESTAMP":"1682622242","LAT":"29.64429","LNG":"-82.34591"},{"SURVEYID":"gb-lry","DEVICEID":"gb-lry-one","TEMP":"35","RH":"88","FLTP":"22","TIMESTAMP":"1682622340","LAT":"29.64430","LNG":"-82.34592"},{"SURVEYID":"gb-lry","DEVICEID":"gb-lry-one","TEMP":"35","RH":"88","FLTP":"23","TIMESTAMP":"1682622437","LAT":"29.64434","LNG":"-82.34592"},{"SURVEYID":"gb-lry","DEVICEID":"gb-lry-one","TEMP":"35","RH":"88","FLTP":"24","TIMESTAMP":"1682622534","LAT":"29.64432","LNG":"-82.34588"},{"SURVEYID":"gb-lry","DEVICEID":"gb-lry-one","TEMP":"34","RH":"88","FLTP":"25","TIMESTAMP":"1682622627","LAT":"29.64432","LNG":"-82.34584"},{"SURVEYID":"gb-lry","DEVICEID":"gb-lry-one","TEMP":"34","RH":"88","FLTP":"26","TIMESTAMP":"1682622720","LAT":"29.64433","LNG":"-82.34592"},{"SURVEYID":"gb-lry","DEVICEID":"gb-lry-one","TEMP":"34","RH":"88","FLTP":"27","TIMESTAMP":"1682622813","LAT":"29.64429","LNG":"-82.34578"},{"SURVEYID":"gb-lry","DEVICEID":"gb-lry-one","TEMP":"34","RH":"88","FLTP":"28","TIMESTAMP":"1682622910","LAT":"29.64423","LNG":"-82.34595"},{"SURVEYID":"gb-lry","DEVICEID":"gb-lry-one","TEMP":"34","RH":"88","FLTP":"29","TIMESTAMP":"1682623004","LAT":"29.64434","LNG":"-82.34595"},{"SURVEYID":"gb-lry","DEVICEID":"gb-lry-one","TEMP":"34","RH":"88","FLTP":"30","TIMESTAMP":"1682623099","LAT":"29.64422","LNG":"-82.34589"},{"SURVEYID":"gb-lry","DEVICEID":"gb-lry-one","TEMP":"34","RH":"88","FLTP":"31","TIMESTAMP":"1682623194","LAT":"29.64432","LNG":"-82.34593"},{"SURVEYID":"gb-lry","DEVICEID":"gb-lry-one","TEMP":"33","RH":"88","FLTP":"32","TIMESTAMP":"1682623289","LAT":"29.64441","LNG":"-82.34592"},{"SURVEYID":"gb-lry","DEVICEID":"gb-lry-one","TEMP":"33","RH":"88","FLTP":"33","TIMESTAMP":"1682623388","LAT":"29.64446","LNG":"-82.34597"},{"SURVEYID":"gb-lry","DEVICEID":"gb-lry-one","TEMP":"33","RH":"88","FLTP":"34","TIMESTAMP":"1682623483","LAT":"29.64437","LNG":"-82.34599"},{"SURVEYID":"gb-lry","DEVICEID":"gb-lry-one","TEMP":"33","RH":"88","FLTP":"35","TIMESTAMP":"1682623578","LAT":"29.64439","LNG":"-82.34601"},{"SURVEYID":"gb-lry","DEVICEID":"gb-lry-one","TEMP":"33","RH":"88","FLTP":"36","TIMESTAMP":"1682623673","LAT":"29.64432","LNG":"-82.34601"},{"SURVEYID":"gb-lry","DEVICEID":"gb-lry-one","TEMP":"32","RH":"88","FLTP":"37","TIMESTAMP":"1682623777","LAT":"29.64439","LNG":"-82.34605"},{"SURVEYID":"gb-lry","DEVICEID":"gb-lry-one","TEMP":"32","RH":"88","FLTP":"38","TIMESTAMP":"1682623873","LAT":"29.64426","LNG":"-82.34603"},{"SURVEYID":"gb-lry","DEVICEID":"gb-lry-one","TEMP":"32","RH":"88","FLTP":"39","TIMESTAMP":"1682623968","LAT":"29.64435","LNG":"-82.34601"},{"SURVEYID":"gb-lry","DEVICEID":"gb-lry-one","TEMP":"32","RH":"88","FLTP":"40","TIMESTAMP":"1682624063","LAT":"29.64431","LNG":"-82.34603"},{"SURVEYID":"gb-lry","DEVICEID":"gb-lry-one","TEMP":"31","RH":"88","FLTP":"41","TIMESTAMP":"1682624159","LAT":"29.64417","LNG":"-82.34597"},{"SURVEYID":"gb-lry","DEVICEID":"gb-lry-one","TEMP":"31","RH":"88","FLTP":"42","TIMESTAMP":"1682624258","LAT":"29.64446","LNG":"-82.34590"},{"SURVEYID":"gb-lry","DEVICEID":"gb-lry-one","TEMP":"31","RH":"89","FLTP":"43","TIMESTAMP":"1682624353","LAT":"29.64452","LNG":"-82.34599"},{"SURVEYID":"gb-lry","DEVICEID":"gb-lry-one","TEMP":"31","RH":"89","FLTP":"44","TIMESTAMP":"1682624449","LAT":"29.64457","LNG":"-82.34589"},{"SURVEYID":"gb-lry","DEVICEID":"gb-lry-one","TEMP":"29","RH":"85","FLTP":"46","TIMESTAMP":"1682624979","LAT":"0.00000","LNG":"0.00000"},{"SURVEYID":"gb-lry","DEVICEID":"gb-lry-one","TEMP":"29","RH":"85","FLTP":"46","TIMESTAMP":"1682624979","LAT":"0.00000","LNG":"0.00000"},{"SURVEYID":"gb-lry","DEVICEID":"gb-lry-one","TEMP":"29","RH":"85","FLTP":"46","TIMESTAMP":"1682624979","LAT":"0.00000","LNG":"0.00000"},{"SURVEYID":"gb-lry","DEVICEID":"gb-lry-one","TEMP":"29","RH":"85","FLTP":"46","TIMESTAMP":"1682624979","LAT":"0.00000","LNG":"0.00000"},{"SURVEYID":"gb-lry","DEVICEID":"gb-lry-one","TEMP":"29","RH":"85","FLTP":"46","TIMESTAMP":"1682624979","LAT":"0.00000","LNG":"0.00000"},{"SURVEYID":"gb-lry","DEVICEID":"gb-lry-one","TEMP":"29","RH":"85","FLTP":"46","TIMESTAMP":"1682624979","LAT":"0.00000","LNG":"0.00000"},{"SURVEYID":"gb-lry","DEVICEID":"gb-lry-one","TEMP":"29","RH":"85","FLTP":"46","TIMESTAMP":"1682624979","LAT":"0.00000","LNG":"0.00000"},{"SURVEYID":"gb-lry","DEVICEID":"gb-lry-one","TEMP":"29","RH":"85","FLTP":"46","TIMESTAMP":"1682624979","LAT":"0.00000","LNG":"0.00000"},{"SURVEYID":"gb-lry","DEVICEID":"gb-lry-one","TEMP":"29","RH":"85","FLTP":"46","TIMESTAMP":"1682624979","LAT":"0.00000","LNG":"0.00000"},{"SURVEYID":"gb-lry","DEVICEID":"gb-lry-one","TEMP":"29","RH":"85","FLTP":"46","TIMESTAMP":"1682624979","LAT":"0.00000","LNG":"0.00000"},{"SURVEYID":"gb-lry","DEVICEID":"gb-lry-one","TEMP":"29","RH":"85","FLTP":"46","TIMESTAMP":"1682624979","LAT":"0.00000","LNG":"0.00000"},{"SURVEYID":"gb-lry","DEVICEID":"gb-lry-one","TEMP":"29","RH":"85","FLTP":"46","TIMESTAMP":"1682624979","LAT":"0.00000","LNG":"0.00000"},{"SURVEYID":"gb-lry","DEVICEID":"gb-lry-one","TEMP":"29","RH":"85","FLTP":"46","TIMESTAMP":"1682624979","LAT":"0.00000","LNG":"0.00000"},{"SURVEYID":"gb-lry","DEVICEID":"gb-lry-one","TEMP":"29","RH":"85","FLTP":"46","TIMESTAMP":"1682624979","LAT":"0.00000","LNG":"0.00000"},{"SURVEYID":"gb-lry","DEVICEID":"gb-lry-one","TEMP":"29","RH":"85","FLTP":"46","TIMESTAMP":"1682624979","LAT":"0.00000","LNG":"0.00000"},{"SURVEYID":"gb-lry","DEVICEID":"gb-lry-one","TEMP":"29","RH":"85","FLTP":"46","TIMESTAMP":"1682624979","LAT":"0.00000","LNG":"0.00000"},{"SURVEYID":"gb-lry","DEVICEID":"gb-lry-one","TEMP":"29","RH":"85","FLTP":"46","TIMESTAMP":"1682624979","LAT":"0.00000","LNG":"0.00000"},{"SURVEYID":"gb-lry","DEVICEID":"gb-lry-one","TEMP":"29","RH":"85","FLTP":"46","TIMESTAMP":"1682624979","LAT":"0.00000","LNG":"0.00000"},{"SURVEYID":"gb-lry","DEVICEID":"gb-lry-one","TEMP":"29","RH":"85","FLTP":"46","TIMESTAMP":"1682624979","LAT":"0.00000","LNG":"0.00000"},{"SURVEYID":"gb-lry","DEVICEID":"gb-lry-one","TEMP":"29","RH":"85","FLTP":"46","TIMESTAMP":"1682624979","LAT":"0.00000","LNG":"0.00000"},{"SURVEYID":"gb-lry","DEVICEID":"gb-lry-one","TEMP":"29","RH":"85","FLTP":"46","TIMESTAMP":"1682624979","LAT":"0.00000","LNG":"0.00000"},{"SURVEYID":"gb-lry","DEVICEID":"gb-lry-one","TEMP":"29","RH":"85","FLTP":"46","TIMESTAMP":"1682624979","LAT":"0.00000","LNG":"0.00000"},{"SURVEYID":"gb-lry","DEVICEID":"gb-lry-one","TEMP":"29","RH":"85","FLTP":"46","TIMESTAMP":"1682624979","LAT":"0.00000","LNG":"0.00000"},{"SURVEYID":"gb-lry","DEVICEID":"gb-lry-one","TEMP":"29","RH":"85","FLTP":"46","TIMESTAMP":"1682624979","LAT":"0.00000","LNG":"0.00000"},{"SURVEYID":"gb-lry","DEVICEID":"gb-lry-one","TEMP":"29","RH":"85","FLTP":"46","TIMESTAMP":"1682624979","LAT":"0.00000","LNG":"0.00000"},{"SURVEYID":"gb-lry","DEVICEID":"gb-lry-one","TEMP":"29","RH":"85","FLTP":"46","TIMESTAMP":"1682624979","LAT":"0.00000","LNG":"0.00000"},{"SURVEYID":"gb-lry","DEVICEID":"gb-lry-one","TEMP":"29","RH":"85","FLTP":"46","TIMESTAMP":"1682624979","LAT":"0.00000","LNG":"0.00000"},{"SURVEYID":"gb-lry","DEVICEID":"gb-lry-one","TEMP":"29","RH":"85","FLTP":"46","TIMESTAMP":"1682624979","LAT":"0.00000","LNG":"0.00000"},{"SURVEYID":"gb-lry","DEVICEID":"gb-lry-one","TEMP":"29","RH":"85","FLTP":"46","TIMESTAMP":"1682624979","LAT":"0.00000","LNG":"0.00000"},{"SURVEYID":"gb-lry","DEVICEID":"gb-lry-one","TEMP":"29","RH":"85","FLTP":"46","TIMESTAMP":"1682624979","LAT":"0.00000","LNG":"0.00000"},{"SURVEYID":"gb-lry","DEVICEID":"gb-lry-one","TEMP":"29","RH":"85","FLTP":"46","TIMESTAMP":"1682624979","LAT":"0.00000","LNG":"0.00000"},{"SURVEYID":"gb-lry","DEVICEID":"gb-lry-one","TEMP":"29","RH":"85","FLTP":"46","TIMESTAMP":"1682624979","LAT":"0.00000","LNG":"0.00000"},{"SURVEYID":"gb-lry","DEVICEID":"gb-lry-one","TEMP":"29","RH":"85","FLTP":"46","TIMESTAMP":"1682624979","LAT":"0.00000","LNG":"0.00000"},{"SURVEYID":"gb-lry","DEVICEID":"gb-lry-one","TEMP":"29","RH":"85","FLTP":"46","TIMESTAMP":"1682624979","LAT":"0.00000","LNG":"0.00000"},{"SURVEYID":"gb-lry","DEVICEID":"gb-lry-one","TEMP":"29","RH":"85","FLTP":"46","TIMESTAMP":"1682624979","LAT":"0.00000","LNG":"0.00000"},{"SURVEYID":"gb-lry","DEVICEID":"gb-lry-one","TEMP":"29","RH":"85","FLTP":"46","TIMESTAMP":"1682624979","LAT":"0.00000","LNG":"0.00000"},{"SURVEYID":"gb-lry","DEVICEID":"gb-lry-one","TEMP":"29","RH":"85","FLTP":"46","TIMESTAMP":"1682624979","LAT":"0.00000","LNG":"0.00000"},{"SURVEYID":"gb-lry","DEVICEID":"gb-lry-one","TEMP":"29","RH":"85","FLTP":"46","TIMESTAMP":"1682624979","LAT":"0.00000","LNG":"0.00000"},{"SURVEYID":"gb-lry","DEVICEID":"gb-lry-one","TEMP":"29","RH":"85","FLTP":"46","TIMESTAMP":"1682624979","LAT":"0.00000","LNG":"0.00000"},{"SURVEYID":"gb-lry","DEVICEID":"gb-lry-one","TEMP":"29","RH":"85","FLTP":"46","TIMESTAMP":"1682624979","LAT":"0.00000","LNG":"0.00000"},{"SURVEYID":"gb-lry","DEVICEID":"gb-lry-one","TEMP":"29","RH":"85","FLTP":"46","TIMESTAMP":"1682624979","LAT":"0.00000","LNG":"0.00000"},{"SURVEYID":"gb-lry","DEVICEID":"gb-lry-one","TEMP":"29","RH":"85","FLTP":"46","TIMESTAMP":"1682624979","LAT":"0.00000","LNG":"0.00000"},{"SURVEYID":"gb-lry","DEVICEID":"gb-lry-one","TEMP":"29","RH":"85","FLTP":"46","TIMESTAMP":"1682624979","LAT":"0.00000","LNG":"0.00000"},{"SURVEYID":"gb-lry","DEVICEID":"gb-lry-one","TEMP":"29","RH":"85","FLTP":"46","TIMESTAMP":"1682624979","LAT":"0.00000","LNG":"0.00000"},{"SURVEYID":"gb-lry","DEVICEID":"gb-lry-one","TEMP":"29","RH":"85","FLTP":"46","TIMESTAMP":"1682624979","LAT":"0.00000","LNG":"0.00000"},{"SURVEYID":"gb-lry","DEVICEID":"gb-lry-one","TEMP":"29","RH":"85","FLTP":"46","TIMESTAMP":"1682624979","LAT":"0.00000","LNG":"0.00000"},{"SURVEYID":"gb-lry","DEVICEID":"gb-lry-one","TEMP":"29","RH":"85","FLTP":"46","TIMESTAMP":"1682624979","LAT":"0.00000","LNG":"0.00000"},{"SURVEYID":"gb-lry","DEVICEID":"gb-lry-one","TEMP":"29","RH":"85","FLTP":"46","TIMESTAMP":"1682624979","LAT":"0.00000","LNG":"0.00000"},{"SURVEYID":"gb-lry","DEVICEID":"gb-lry-one","TEMP":"29","RH":"85","FLTP":"46","TIMESTAMP":"1682624979","LAT":"0.00000","LNG":"0.00000"},{"SURVEYID":"gb-lry","DEVICEID":"gb-lry-one","TEMP":"29","RH":"85","FLTP":"46","TIMESTAMP":"1682624979","LAT":"0.00000","LNG":"0.00000"},{"SURVEYID":"gb-lry","DEVICEID":"gb-lry-one","TEMP":"29","RH":"85","FLTP":"46","TIMESTAMP":"1682624979","LAT":"0.00000","LNG":"0.00000"},{"SURVEYID":"gb-lry","DEVICEID":"gb-lry-one","TEMP":"29","RH":"85","FLTP":"46","TIMESTAMP":"1682624979","LAT":"0.00000","LNG":"0.00000"},{"SURVEYID":"gb-lry","DEVICEID":"gb-lry-one","TEMP":"29","RH":"85","FLTP":"46","TIMESTAMP":"1682624979","LAT":"0.00000","LNG":"0.00000"},{"SURVEYID":"gb-lry","DEVICEID":"gb-lry-one","TEMP":"29","RH":"85","FLTP":"46","TIMESTAMP":"1682624979","LAT":"0.00000","LNG":"0.00000"},{"SURVEYID":"gb-lry","DEVICEID":"gb-lry-one","TEMP":"29","RH":"85","FLTP":"46","TIMESTAMP":"1682624979","LAT":"0.00000","LNG":"0.00000"}]